{
	"carName": "audi_r8_lms",
	"basicSetup":
	{
		"tyres":
		{
			"tyreCompound": 0,
			"tyrePressure": [ 9, 9, 7, 7 ]
		},
		"alignment":
		{
			"camber": [ 11, 11, 13, 13 ],
			"toe": [ 24, 24, 63, 63 ],
			"staticCamber": [ -4.1117277145385742, -4.1175136566162109, -3.489762544631958, -3.4958269596099854 ],
			"toeOutLinear": [ 0.00058207655092701316, 0.00058239494683220983, 0.00078562111593782902, 0.00078557332744821906 ],
			"casterLF": 15,
			"casterRF": 15,
			"steerRatio": 5
		},
		"electronics":
		{
			"tC1": 3,
			"tC2": 0,
			"abs": 3,
			"eCUMap": 0,
			"fuelMix": 0,
			"telemetryLaps": 0
		},
		"strategy":
		{
			"fuel": 93,
			"nPitStops": 26,
			"tyreSet": 5,
			"pitStrategy": [
				{
					"fuelToAdd": 0,
					"tyres":
					{
						"tyreCompound": 0,
						"tyrePressure": [ 0, 0, 0, 0 ]
					},
					"tyreSet": 2
				},
				{
					"fuelToAdd": 0,
					"tyres":
					{
						"tyreCompound": 0,
						"tyrePressure": [ 0, 0, 0, 0 ]
					},
					"tyreSet": 2
				},
				{
					"fuelToAdd": 0,
					"tyres":
					{
						"tyreCompound": 0,
						"tyrePressure": [ 0, 0, 0, 0 ]
					},
					"tyreSet": 2
				},
				{
					"fuelToAdd": 0,
					"tyres":
					{
						"tyreCompound": 0,
						"tyrePressure": [ 0, 0, 0, 0 ]
					},
					"tyreSet": 2
				},
				{
					"fuelToAdd": 0,
					"tyres":
					{
						"tyreCompound": 0,
						"tyrePressure": [ 0, 0, 0, 0 ]
					},
					"tyreSet": 2
				},
				{
					"fuelToAdd": 0,
					"tyres":
					{
						"tyreCompound": 0,
						"tyrePressure": [ 0, 0, 0, 0 ]
					},
					"tyreSet": 2
				},
				{
					"fuelToAdd": 0,
					"tyres":
					{
						"tyreCompound": 0,
						"tyrePressure": [ 0, 0, 0, 0 ]
					},
					"tyreSet": 2
				},
				{
					"fuelToAdd": 0,
					"tyres":
					{
						"tyreCompound": 0,
						"tyrePressure": [ 0, 0, 0, 0 ]
					},
					"tyreSet": 2
				},
				{
					"fuelToAdd": 0,
					"tyres":
					{
						"tyreCompound": 0,
						"tyrePressure": [ 0, 0, 0, 0 ]
					},
					"tyreSet": 2
				},
				{
					"fuelToAdd": 0,
					"tyres":
					{
						"tyreCompound": 0,
						"tyrePressure": [ 0, 0, 0, 0 ]
					},
					"tyreSet": 2
				},
				{
					"fuelToAdd": 0,
					"tyres":
					{
						"tyreCompound": 0,
						"tyrePressure": [ 0, 0, 0, 0 ]
					},
					"tyreSet": 2
				},
				{
					"fuelToAdd": 0,
					"tyres":
					{
						"tyreCompound": 0,
						"tyrePressure": [ 0, 0, 0, 0 ]
					},
					"tyreSet": 2
				},
				{
					"fuelToAdd": 0,
					"tyres":
					{
						"tyreCompound": 0,
						"tyrePressure": [ 0, 0, 0, 0 ]
					},
					"tyreSet": 2
				},
				{
					"fuelToAdd": 0,
					"tyres":
					{
						"tyreCompound": 0,
						"tyrePressure": [ 0, 0, 0, 0 ]
					},
					"tyreSet": 2
				},
				{
					"fuelToAdd": 0,
					"tyres":
					{
						"tyreCompound": 0,
						"tyrePressure": [ 0, 0, 0, 0 ]
					},
					"tyreSet": 2
				},
				{
					"fuelToAdd": 0,
					"tyres":
					{
						"tyreCompound": 0,
						"tyrePressure": [ 0, 0, 0, 0 ]
					},
					"tyreSet": 2
				},
				{
					"fuelToAdd": 0,
					"tyres":
					{
						"tyreCompound": 0,
						"tyrePressure": [ 0, 0, 0, 0 ]
					},
					"tyreSet": 2
				},
				{
					"fuelToAdd": 0,
					"tyres":
					{
						"tyreCompound": 0,
						"tyrePressure": [ 0, 0, 0, 0 ]
					},
					"tyreSet": 2
				},
				{
					"fuelToAdd": 0,
					"tyres":
					{
						"tyreCompound": 0,
						"tyrePressure": [ 0, 0, 0, 0 ]
					},
					"tyreSet": 2
				},
				{
					"fuelToAdd": 0,
					"tyres":
					{
						"tyreCompound": 0,
						"tyrePressure": [ 0, 0, 0, 0 ]
					},
					"tyreSet": 2
				},
				{
					"fuelToAdd": 0,
					"tyres":
					{
						"tyreCompound": 0,
						"tyrePressure": [ 0, 0, 0, 0 ]
					},
					"tyreSet": 2
				},
				{
					"fuelToAdd": 0,
					"tyres":
					{
						"tyreCompound": 0,
						"tyrePressure": [ 0, 0, 0, 0 ]
					},
					"tyreSet": 2
				},
				{
					"fuelToAdd": 0,
					"tyres":
					{
						"tyreCompound": 0,
						"tyrePressure": [ 0, 0, 0, 0 ]
					},
					"tyreSet": 2
				},
				{
					"fuelToAdd": 0,
					"tyres":
					{
						"tyreCompound": 0,
						"tyrePressure": [ 0, 0, 0, 0 ]
					},
					"tyreSet": 2
				},
				{
					"fuelToAdd": 0,
					"tyres":
					{
						"tyreCompound": 0,
						"tyrePressure": [ 0, 0, 0, 0 ]
					},
					"tyreSet": 2
				},
				{
					"fuelToAdd": 0,
					"tyres":
					{
						"tyreCompound": 0,
						"tyrePressure": [ 0, 0, 0, 0 ]
					},
					"tyreSet": 2
				},
				{
					"fuelToAdd": 0,
					"tyres":
					{
						"tyreCompound": 0,
						"tyrePressure": [ 13, 13, 9, 10 ]
					},
					"tyreSet": 2
				},
				{
					"fuelToAdd": 0,
					"tyres":
					{
						"tyreCompound": 0,
						"tyrePressure": [ 147, 0, 0, 0 ]
					},
					"tyreSet": 2
				}
			],
			"fuelPerLap": 3.9000000953674316
		}
	},
	"advancedSetup":
	{
		"mechanicalBalance":
		{
			"aRBFront": 3,
			"aRBRear": 1,
			"wheelRate": [ 2, 2, 2, 2 ],
			"bumpStopRateUp": [ 14, 14, 2, 2 ],
			"bumpStopRateDn": [ 0, 0, 10, 10 ],
			"bumpStopWindow": [ 20, 20, 60, 60 ],
			"brakeTorque": 20,
			"brakeBias": 65
		},
		"dampers":
		{
			"bumpSlow": [ 25, 25, 14, 14 ],
			"bumpFast": [ 20, 20, 10, 10 ],
			"reboundSlow": [ 25, 25, 20, 20 ],
			"reboundFast": [ 30, 30, 20, 20 ]
		},
		"aeroBalance":
		{
			"rideHeight": [ 8, 6, 9, 18 ],
			"rodLength": [ 36.96246337890625, 36.96246337890625, 15.140181541442871, 15.140181541442871 ],
			"splitter": 0,
			"rearWing": 4,
			"brakeDuct": [ 3, 3 ]
		},
		"drivetrain":
		{
			"preload": 13
		}
	}
}